tr/Task.py
tr/__init__.py
tr/__main__.py
tr/actions.py
tr/common.py
tr/config.py
tr/logTools.py
pytaskrunner-0.13.2.dist-info/LICENSE
pytaskrunner-0.13.2.dist-info/METADATA
pytaskrunner-0.13.2.dist-info/WHEEL
pytaskrunner-0.13.2.dist-info/entry_points.txt
pytaskrunner-0.13.2.dist-info/top_level.txt
pytaskrunner-0.13.2.dist-info/RECORD
