Metadata-Version: 2.2
Name: pytaskrunner
Version: 0.13.2
Summary: Shell tasks managmement tool
Author-email: Omer Caspi <omer.caspi@gmail.com>
Project-URL: Homepage, https://github.com/omercsp/taskrunner
Classifier: License :: OSI Approved :: MIT License
Classifier: Operating System :: OS Independent
Classifier: Topic :: Utilities
Classifier: Programming Language :: Python
Classifier: Programming Language :: Python :: 3
Classifier: Programming Language :: Python :: 3.10
Classifier: Programming Language :: Python :: 3.11
Classifier: Programming Language :: Python :: 3.12
Requires-Python: <4,>=3.10
License-File: LICENSE
Requires-Dist: argcomplete>=2.0.0
Requires-Dist: pydantic>=2.8
Requires-Dist: setuptools>=72
Requires-Dist: PyYAML<7.0,>=6.0.2
Provides-Extra: devel
Requires-Dist: xeet>=0.5.5; extra == "devel"
